{
  "tasks": [
    {
      "id": "6841aa29e8605de223f0a139",
      "skills": [
        null,
        null
      ],
      "assignedTo": null,
      "availabilities": {}
    }
  ],
  "members": [
    {
      "id": "683af179e9485732c0800697",
      "skills": [],
      "preferences": [],
      "availability": 10,
      "experience": 0
    },
    {
      "id": "683af28de9485732c08006c3",
      "skills": [],
      "preferences": [],
      "availability": 10,
      "experience": 0
    },
    {
      "id": "683af715e9485732c080074b",
      "skills": [],
      "preferences": [],
      "availability": 10,
      "experience": 0
    }
  ]
}